<?xml version="1.0" encoding="utf-8"?>
<!DOCTYPE hibernate-mapping PUBLIC "-//Hibernate/Hibernate Mapping DTD 3.0//EN"
"http://hibernate.sourceforge.net/hibernate-mapping-3.0.dtd">
<!-- 
    Mapping file autogenerated by MyEclipse Persistence Tools
-->
<hibernate-mapping>
    <class name="entity.Information" table="information">
        <id name="informationid" type="java.lang.Integer">
            <column name="informationid" />
            <generator class="native" />
        </id>
        <property name="credit" type="java.lang.Integer">
            <column name="credit"/>
        </property>
        
        <property name="subject" type="java.lang.String">
            <column name="subject"/>
        </property>
        
        <property name="code" type="java.lang.String">
            <column name="code"/>
        </property>
        
        <property name="grade" type="java.lang.Double">
            <column name="grade" />
        </property>
        
        <many-to-one
        	name="user"
        	column="user_userId"
        	class="entity.User"
        	lazy="false"
        	not-null="true"
        />
        
        
        
    </class>
</hibernate-mapping>
